ciq/__init__.py
ciq/client.py
ciq-0.1.0.dist-info/METADATA
ciq-0.1.0.dist-info/WHEEL
ciq-0.1.0.dist-info/top_level.txt
ciq-0.1.0.dist-info/RECORD
