Metadata-Version: 2.4
Name: ciq
Version: 0.1.0
Summary: A minimal CIQ SDK that says Hello World
Author-email: Khushi <your-email@example.com>
License: MIT
Requires-Python: >=3.7
